advent_of_code_explainer/__init__.py
advent_of_code_explainer/__version__.py
advent_of_code_explainer/puzzles/__init__.py
advent_of_code_explainer/puzzles/year_2023/__init__.py
advent_of_code_explainer/puzzles/year_2023/day_1.py
advent_of_code_explainer/puzzles/year_2023/day_2.py
advent_of_code_explainer/puzzles/year_2024/__init__.py
advent_of_code_explainer/puzzles/year_2024/day_1.py
advent_of_code_explainer/puzzles/year_2024/day_2.py
advent_of_code_explainer-0.0.1.dist-info/LICENSE
advent_of_code_explainer-0.0.1.dist-info/METADATA
advent_of_code_explainer-0.0.1.dist-info/WHEEL
advent_of_code_explainer-0.0.1.dist-info/top_level.txt
advent_of_code_explainer-0.0.1.dist-info/RECORD
