Metadata-Version: 2.1
Name: advent-of-code-explainer
Version: 0.0.1
Summary: An "explainer" app for "Advent of Code" puzzles.
Author-email: Skenvy <nathan.a.z.levett@gmail.com>
Maintainer-email: Skenvy <nathan.a.z.levett@gmail.com>
License:                     GNU GENERAL PUBLIC LICENSE
Project-URL: Homepage, https://github.com/Skenvy/advent-of-code-explainer/tree/main/pkg
Project-URL: Download, https://github.com/Skenvy/advent-of-code-explainer/archive/refs/heads/main.zip
Project-URL: Changelog, https://github.com/Skenvy/advent-of-code-explainer/releases
Project-URL: Documentation, https://skenvy.github.io/advent-of-code-explainer/pkg/
Project-URL: BugTracker, https://github.com/Skenvy/advent-of-code-explainer/issues
Project-URL: Funding, https://github.com/sponsors/Skenvy
Project-URL: GitHub, https://github.com/Skenvy/advent-of-code-explainer
Project-URL: PyPI, https://pypi.org/project/advent-of-code-explainer/
Keywords: Advent
Classifier: Programming Language :: Python :: 3
Classifier: License :: OSI Approved :: GNU General Public License v3 (GPLv3)
Classifier: Operating System :: OS Independent
Requires-Python: >=3.10
License-File: LICENSE
